flask_continuum/__init__.py
flask_continuum/mixins.py
flask_continuum/plugin.py
Flask_Continuum-0.1.7.dist-info/LICENSE
Flask_Continuum-0.1.7.dist-info/METADATA
Flask_Continuum-0.1.7.dist-info/WHEEL
Flask_Continuum-0.1.7.dist-info/top_level.txt
Flask_Continuum-0.1.7.dist-info/RECORD
