Metadata-Version: 1.1
Name: Flask-Continuum
Version: 0.1.7
Summary: Model provenance and versioning via SQLAlchemy-Continuum
Home-page: https://github.com/bprinty/Flask-Continuum
Author: Blake Printy
Author-email: bprinty@gmail.com
License: MIT
Keywords: Flask-Continuum,flask,versioning,history,provenance,continuum
Platform: any
Classifier: Environment :: Web Environment
Classifier: Intended Audience :: Developers
Classifier: License :: OSI Approved :: MIT License
Classifier: Operating System :: OS Independent
Classifier: Programming Language :: Python
Classifier: Topic :: Internet :: WWW/HTTP :: Dynamic Content
Classifier: Topic :: Software Development :: Libraries :: Python Modules
Classifier: Natural Language :: English
Classifier: Programming Language :: Python :: 3
Classifier: Programming Language :: Python :: 3.3
Classifier: Programming Language :: Python :: 3.4
Classifier: Programming Language :: Python :: 3.5
Classifier: Programming Language :: Python :: 3.6
Classifier: Programming Language :: Python :: 3.7
